<?xml version="1.0" encoding="UTF-8"?>
<objects serializationModel="Studio.02.01.00">
	<object class="ParameterPreset" id="{094aac90-f140-4b25-8122-f033dd619361}">
		<property name="name">
			<value>LPF</value>
		</property>
		<relationship name="folder">
			<destination>{b49e728f-85cd-4e36-b780-20a3b04782c2}</destination>
		</relationship>
		<relationship name="parameter">
			<destination>{cf42b5a7-0bb5-43be-8aaf-bc64f17f31df}</destination>
		</relationship>
	</object>
	<object class="GameParameter" id="{cf42b5a7-0bb5-43be-8aaf-bc64f17f31df}">
		<property name="initialValue">
			<value>0</value>
		</property>
		<property name="seekSpeed">
			<value>4</value>
		</property>
	</object>
</objects>
