<?xml version="1.0" encoding="UTF-8"?>
<objects serializationModel="Studio.02.01.00">
	<object class="ParameterPreset" id="{cd0a1b2e-8e0e-4ca8-aad1-d111744f6eb4}">
		<property name="name">
			<value>NearingEnd</value>
		</property>
		<relationship name="folder">
			<destination>{02c95295-0716-4ffa-a604-42ead34d865a}</destination>
		</relationship>
		<relationship name="parameter">
			<destination>{acabc52e-9389-46e2-b1c3-86ef6221cb2b}</destination>
		</relationship>
	</object>
	<object class="GameParameter" id="{acabc52e-9389-46e2-b1c3-86ef6221cb2b}">
		<property name="initialValue">
			<value>0</value>
		</property>
	</object>
</objects>
